element_project_generator-0.1.1.dist-info/licenses/LICENSE
templates/__init__.py
templates/main.py
templates/template_proj.py
element_project_generator-0.1.1.dist-info/METADATA
element_project_generator-0.1.1.dist-info/WHEEL
element_project_generator-0.1.1.dist-info/top_level.txt
element_project_generator-0.1.1.dist-info/RECORD
